valdi/__init__.py
valdi/entrypoint.py
valdi/cli/__init__.py
valdi/cli/authenticator.py
valdi/cli/initializer.py
valdi/cli/volume_manager.py
valdi/config/__init__.py
valdi/config/settings.py
valdi/router/__init__.py
valdi/router/service_router.py
valdi-0.2.5.dist-info/LICENSE
valdi-0.2.5.dist-info/METADATA
valdi-0.2.5.dist-info/WHEEL
valdi-0.2.5.dist-info/entry_points.txt
valdi-0.2.5.dist-info/top_level.txt
valdi-0.2.5.dist-info/RECORD
