Metadata-Version: 2.1
Name: valdi
Version: 0.2.5
Summary: A command-line utility for managing VALDI cloud resources
Author-email: VALDI <contact@valdi.ai>
License: MIT License
Project-URL: Homepage, https://valdi.ai
Project-URL: Documentation, https://docs.valdi.ai
Project-URL: Repository, https://github.com/valdi-labs/valdi-cli
Keywords: valdi,gpu,cloud,cli,storage,volumes
Classifier: Development Status :: 3 - Alpha
Classifier: Intended Audience :: Developers
Classifier: Intended Audience :: System Administrators
Classifier: Intended Audience :: Information Technology
Requires-Python: >=3.8
License-File: LICENSE
Requires-Dist: certifi >=2023.11.17
Requires-Dist: charset-normalizer ==3.3.2
Requires-Dist: idna >=3.6
Requires-Dist: PyJWT >=2.8.0
Requires-Dist: requests >=2.31.0
Requires-Dist: urllib3 >=2.1.0
